varmeta/__init__.py
varmeta/vars.py
varmeta-0.1.3.dist-info/METADATA
varmeta-0.1.3.dist-info/WHEEL
varmeta-0.1.3.dist-info/entry_points.txt
varmeta-0.1.3.dist-info/licenses/LICENSE
varmeta-0.1.3.dist-info/RECORD
