Metadata-Version: 2.4
Name: varmeta
Version: 0.1.3
Summary: Lightweight variable metadata management.
Author-email: Reuben Rusk <pythoro@mindquip.com>
License-File: LICENSE
Requires-Python: >=3.11
Requires-Dist: numpy>=1.11.0
Requires-Dist: pandas>=2.3.1
